[
  {
    "id": "M001",
    "homeTeamId": "MEX",
    "awayTeamId": "RSA",
    "matchTime": "2026-06-11T19:00:00Z",
    "venue": "Estadio Azteca, Mexico City",
    "group": "A",
    "stage": "group",
    "status": "pending"
  },
  {
    "id": "M002",
    "homeTeamId": "KOR",
    "awayTeamId": "CZE",
    "matchTime": "2026-06-12T02:00:00Z",
    "venue": "Estadio Akron, Guadalajara",
    "group": "A",
    "stage": "group",
    "status": "pending"
  },
  {
    "id": "M003",
    "homeTeamId": "CZE",
    "awayTeamId": "RSA",
    "matchTime": "2026-06-18T16:00:00Z",
    "venue": "Mercedes-Benz Stadium, Atlanta",
    "group": "A",
    "stage": "group",
    "status": "pending"
  },
  {
    "id": "M004",
    "homeTeamId": "MEX",
    "awayTeamId": "KOR",
    "matchTime": "2026-06-19T01:00:00Z",
    "venue": "Estadio Akron, Guadalajara",
    "group": "A",
    "stage": "group",
    "status": "pending"
  },
  {
    "id": "M005",
    "homeTeamId": "CZE",
    "awayTeamId": "MEX",
    "matchTime": "2026-06-25T01:00:00Z",
    "venue": "Estadio Azteca, Mexico City",
    "group": "A",
    "stage": "group",
    "status": "pending"
  },
  {
    "id": "M006",
    "homeTeamId": "RSA",
    "awayTeamId": "KOR",
    "matchTime": "2026-06-25T01:00:00Z",
    "venue": "Estadio BBVA, Monterrey",
    "group": "A",
    "stage": "group",
    "status": "pending"
  },
  {
    "id": "M007",
    "homeTeamId": "CAN",
    "awayTeamId": "BIH",
    "matchTime": "2026-06-12T19:00:00Z",
    "venue": "BMO Field, Toronto",
    "group": "B",
    "stage": "group",
    "status": "pending"
  },
  {
    "id": "M008",
    "homeTeamId": "QAT",
    "awayTeamId": "SUI",
    "matchTime": "2026-06-13T19:00:00Z",
    "venue": "Levi's Stadium, San Francisco Bay Area",
    "group": "B",
    "stage": "group",
    "status": "pending"
  },
  {
    "id": "M009",
    "homeTeamId": "SUI",
    "awayTeamId": "BIH",
    "matchTime": "2026-06-18T19:00:00Z",
    "venue": "SoFi Stadium, Los Angeles",
    "group": "B",
    "stage": "group",
    "status": "pending"
  },
  {
    "id": "M010",
    "homeTeamId": "CAN",
    "awayTeamId": "QAT",
    "matchTime": "2026-06-18T22:00:00Z",
    "venue": "BC Place, Vancouver",
    "group": "B",
    "stage": "group",
    "status": "pending"
  },
  {
    "id": "M011",
    "homeTeamId": "SUI",
    "awayTeamId": "CAN",
    "matchTime": "2026-06-24T19:00:00Z",
    "venue": "BC Place, Vancouver",
    "group": "B",
    "stage": "group",
    "status": "pending"
  },
  {
    "id": "M012",
    "homeTeamId": "BIH",
    "awayTeamId": "QAT",
    "matchTime": "2026-06-24T19:00:00Z",
    "venue": "Lumen Field, Seattle",
    "group": "B",
    "stage": "group",
    "status": "pending"
  },
  {
    "id": "M013",
    "homeTeamId": "BRA",
    "awayTeamId": "MAR",
    "matchTime": "2026-06-13T22:00:00Z",
    "venue": "MetLife Stadium, New York/New Jersey",
    "group": "C",
    "stage": "group",
    "status": "pending"
  },
  {
    "id": "M014",
    "homeTeamId": "HAI",
    "awayTeamId": "SCO",
    "matchTime": "2026-06-14T01:00:00Z",
    "venue": "Gillette Stadium, Boston",
    "group": "C",
    "stage": "group",
    "status": "pending"
  },
  {
    "id": "M015",
    "homeTeamId": "SCO",
    "awayTeamId": "MAR",
    "matchTime": "2026-06-19T22:00:00Z",
    "venue": "Gillette Stadium, Boston",
    "group": "C",
    "stage": "group",
    "status": "pending"
  },
  {
    "id": "M016",
    "homeTeamId": "BRA",
    "awayTeamId": "HAI",
    "matchTime": "2026-06-20T01:00:00Z",
    "venue": "Lincoln Financial Field, Philadelphia",
    "group": "C",
    "stage": "group",
    "status": "pending"
  },
  {
    "id": "M017",
    "homeTeamId": "SCO",
    "awayTeamId": "BRA",
    "matchTime": "2026-06-24T22:00:00Z",
    "venue": "Hard Rock Stadium, Miami",
    "group": "C",
    "stage": "group",
    "status": "pending"
  },
  {
    "id": "M018",
    "homeTeamId": "MAR",
    "awayTeamId": "HAI",
    "matchTime": "2026-06-24T22:00:00Z",
    "venue": "Mercedes-Benz Stadium, Atlanta",
    "group": "C",
    "stage": "group",
    "status": "pending"
  },
  {
    "id": "M019",
    "homeTeamId": "USA",
    "awayTeamId": "PAR",
    "matchTime": "2026-06-13T01:00:00Z",
    "venue": "SoFi Stadium, Los Angeles",
    "group": "D",
    "stage": "group",
    "status": "pending"
  },
  {
    "id": "M020",
    "homeTeamId": "AUS",
    "awayTeamId": "TUR",
    "matchTime": "2026-06-13T04:00:00Z",
    "venue": "BC Place, Vancouver",
    "group": "D",
    "stage": "group",
    "status": "pending"
  },
  {
    "id": "M021",
    "homeTeamId": "USA",
    "awayTeamId": "AUS",
    "matchTime": "2026-06-19T19:00:00Z",
    "venue": "Lumen Field, Seattle",
    "group": "D",
    "stage": "group",
    "status": "pending"
  },
  {
    "id": "M022",
    "homeTeamId": "TUR",
    "awayTeamId": "PAR",
    "matchTime": "2026-06-20T04:00:00Z",
    "venue": "Levi's Stadium, San Francisco Bay Area",
    "group": "D",
    "stage": "group",
    "status": "pending"
  },
  {
    "id": "M023",
    "homeTeamId": "TUR",
    "awayTeamId": "USA",
    "matchTime": "2026-06-26T02:00:00Z",
    "venue": "SoFi Stadium, Los Angeles",
    "group": "D",
    "stage": "group",
    "status": "pending"
  },
  {
    "id": "M024",
    "homeTeamId": "PAR",
    "awayTeamId": "AUS",
    "matchTime": "2026-06-26T02:00:00Z",
    "venue": "Levi's Stadium, San Francisco Bay Area",
    "group": "D",
    "stage": "group",
    "status": "pending"
  },
  {
    "id": "M025",
    "homeTeamId": "GER",
    "awayTeamId": "CUW",
    "matchTime": "2026-06-14T17:00:00Z",
    "venue": "NRG Stadium, Houston",
    "group": "E",
    "stage": "group",
    "status": "pending"
  },
  {
    "id": "M026",
    "homeTeamId": "CIV",
    "awayTeamId": "ECU",
    "matchTime": "2026-06-14T23:00:00Z",
    "venue": "Lincoln Financial Field, Philadelphia",
    "group": "E",
    "stage": "group",
    "status": "pending"
  },
  {
    "id": "M027",
    "homeTeamId": "GER",
    "awayTeamId": "CIV",
    "matchTime": "2026-06-20T20:00:00Z",
    "venue": "BMO Field, Toronto",
    "group": "E",
    "stage": "group",
    "status": "pending"
  },
  {
    "id": "M028",
    "homeTeamId": "ECU",
    "awayTeamId": "CUW",
    "matchTime": "2026-06-21T00:00:00Z",
    "venue": "Arrowhead Stadium, Kansas City",
    "group": "E",
    "stage": "group",
    "status": "pending"
  },
  {
    "id": "M029",
    "homeTeamId": "ECU",
    "awayTeamId": "GER",
    "matchTime": "2026-06-25T20:00:00Z",
    "venue": "MetLife Stadium, New York/New Jersey",
    "group": "E",
    "stage": "group",
    "status": "pending"
  },
  {
    "id": "M030",
    "homeTeamId": "CUW",
    "awayTeamId": "CIV",
    "matchTime": "2026-06-25T20:00:00Z",
    "venue": "Lincoln Financial Field, Philadelphia",
    "group": "E",
    "stage": "group",
    "status": "pending"
  },
  {
    "id": "M031",
    "homeTeamId": "NED",
    "awayTeamId": "JPN",
    "matchTime": "2026-06-14T20:00:00Z",
    "venue": "AT&T Stadium, Dallas",
    "group": "F",
    "stage": "group",
    "status": "pending"
  },
  {
    "id": "M032",
    "homeTeamId": "SWE",
    "awayTeamId": "TUN",
    "matchTime": "2026-06-15T02:00:00Z",
    "venue": "Estadio BBVA, Monterrey",
    "group": "F",
    "stage": "group",
    "status": "pending"
  },
  {
    "id": "M033",
    "homeTeamId": "NED",
    "awayTeamId": "SWE",
    "matchTime": "2026-06-20T17:00:00Z",
    "venue": "NRG Stadium, Houston",
    "group": "F",
    "stage": "group",
    "status": "pending"
  },
  {
    "id": "M034",
    "homeTeamId": "TUN",
    "awayTeamId": "JPN",
    "matchTime": "2026-06-21T04:00:00Z",
    "venue": "Estadio BBVA, Monterrey",
    "group": "F",
    "stage": "group",
    "status": "pending"
  },
  {
    "id": "M035",
    "homeTeamId": "JPN",
    "awayTeamId": "SWE",
    "matchTime": "2026-06-25T23:00:00Z",
    "venue": "AT&T Stadium, Dallas",
    "group": "F",
    "stage": "group",
    "status": "pending"
  },
  {
    "id": "M036",
    "homeTeamId": "TUN",
    "awayTeamId": "NED",
    "matchTime": "2026-06-25T23:00:00Z",
    "venue": "Arrowhead Stadium, Kansas City",
    "group": "F",
    "stage": "group",
    "status": "pending"
  },
  {
    "id": "M037",
    "homeTeamId": "IRN",
    "awayTeamId": "NZL",
    "matchTime": "2026-06-16T01:00:00Z",
    "venue": "SoFi Stadium, Los Angeles",
    "group": "G",
    "stage": "group",
    "status": "pending"
  },
  {
    "id": "M038",
    "homeTeamId": "BEL",
    "awayTeamId": "EGY",
    "matchTime": "2026-06-15T19:00:00Z",
    "venue": "Lumen Field, Seattle",
    "group": "G",
    "stage": "group",
    "status": "pending"
  },
  {
    "id": "M039",
    "homeTeamId": "BEL",
    "awayTeamId": "IRN",
    "matchTime": "2026-06-21T19:00:00Z",
    "venue": "SoFi Stadium, Los Angeles",
    "group": "G",
    "stage": "group",
    "status": "pending"
  },
  {
    "id": "M040",
    "homeTeamId": "NZL",
    "awayTeamId": "EGY",
    "matchTime": "2026-06-22T01:00:00Z",
    "venue": "BC Place, Vancouver",
    "group": "G",
    "stage": "group",
    "status": "pending"
  },
  {
    "id": "M041",
    "homeTeamId": "EGY",
    "awayTeamId": "IRN",
    "matchTime": "2026-06-27T03:00:00Z",
    "venue": "Lumen Field, Seattle",
    "group": "G",
    "stage": "group",
    "status": "pending"
  },
  {
    "id": "M042",
    "homeTeamId": "NZL",
    "awayTeamId": "BEL",
    "matchTime": "2026-06-27T03:00:00Z",
    "venue": "BC Place, Vancouver",
    "group": "G",
    "stage": "group",
    "status": "pending"
  },
  {
    "id": "M043",
    "homeTeamId": "ESP",
    "awayTeamId": "CPV",
    "matchTime": "2026-06-15T16:00:00Z",
    "venue": "Mercedes-Benz Stadium, Atlanta",
    "group": "H",
    "stage": "group",
    "status": "pending"
  },
  {
    "id": "M044",
    "homeTeamId": "KSA",
    "awayTeamId": "URU",
    "matchTime": "2026-06-15T22:00:00Z",
    "venue": "Hard Rock Stadium, Miami",
    "group": "H",
    "stage": "group",
    "status": "pending"
  },
  {
    "id": "M045",
    "homeTeamId": "ESP",
    "awayTeamId": "KSA",
    "matchTime": "2026-06-21T16:00:00Z",
    "venue": "Mercedes-Benz Stadium, Atlanta",
    "group": "H",
    "stage": "group",
    "status": "pending"
  },
  {
    "id": "M046",
    "homeTeamId": "URU",
    "awayTeamId": "CPV",
    "matchTime": "2026-06-21T22:00:00Z",
    "venue": "Hard Rock Stadium, Miami",
    "group": "H",
    "stage": "group",
    "status": "pending"
  },
  {
    "id": "M047",
    "homeTeamId": "CPV",
    "awayTeamId": "KSA",
    "matchTime": "2026-06-27T00:00:00Z",
    "venue": "NRG Stadium, Houston",
    "group": "H",
    "stage": "group",
    "status": "pending"
  },
  {
    "id": "M048",
    "homeTeamId": "URU",
    "awayTeamId": "ESP",
    "matchTime": "2026-06-27T00:00:00Z",
    "venue": "Estadio Akron, Guadalajara",
    "group": "H",
    "stage": "group",
    "status": "pending"
  },
  {
    "id": "M049",
    "homeTeamId": "FRA",
    "awayTeamId": "SEN",
    "matchTime": "2026-06-16T19:00:00Z",
    "venue": "MetLife Stadium, New York/New Jersey",
    "group": "I",
    "stage": "group",
    "status": "pending"
  },
  {
    "id": "M050",
    "homeTeamId": "IRQ",
    "awayTeamId": "NOR",
    "matchTime": "2026-06-16T22:00:00Z",
    "venue": "Gillette Stadium, Boston",
    "group": "I",
    "stage": "group",
    "status": "pending"
  },
  {
    "id": "M051",
    "homeTeamId": "FRA",
    "awayTeamId": "IRQ",
    "matchTime": "2026-06-22T21:00:00Z",
    "venue": "Lincoln Financial Field, Philadelphia",
    "group": "I",
    "stage": "group",
    "status": "pending"
  },
  {
    "id": "M052",
    "homeTeamId": "NOR",
    "awayTeamId": "SEN",
    "matchTime": "2026-06-23T00:00:00Z",
    "venue": "MetLife Stadium, New York/New Jersey",
    "group": "I",
    "stage": "group",
    "status": "pending"
  },
  {
    "id": "M053",
    "homeTeamId": "NOR",
    "awayTeamId": "FRA",
    "matchTime": "2026-06-26T19:00:00Z",
    "venue": "Gillette Stadium, Boston",
    "group": "I",
    "stage": "group",
    "status": "pending"
  },
  {
    "id": "M054",
    "homeTeamId": "SEN",
    "awayTeamId": "IRQ",
    "matchTime": "2026-06-26T19:00:00Z",
    "venue": "BMO Field, Toronto",
    "group": "I",
    "stage": "group",
    "status": "pending"
  },
  {
    "id": "M055",
    "homeTeamId": "ARG",
    "awayTeamId": "ALG",
    "matchTime": "2026-06-17T01:00:00Z",
    "venue": "Arrowhead Stadium, Kansas City",
    "group": "J",
    "stage": "group",
    "status": "pending"
  },
  {
    "id": "M056",
    "homeTeamId": "AUT",
    "awayTeamId": "JOR",
    "matchTime": "2026-06-17T04:00:00Z",
    "venue": "Levi's Stadium, San Francisco Bay Area",
    "group": "J",
    "stage": "group",
    "status": "pending"
  },
  {
    "id": "M057",
    "homeTeamId": "ARG",
    "awayTeamId": "AUT",
    "matchTime": "2026-06-22T17:00:00Z",
    "venue": "AT&T Stadium, Dallas",
    "group": "J",
    "stage": "group",
    "status": "pending"
  },
  {
    "id": "M058",
    "homeTeamId": "JOR",
    "awayTeamId": "ALG",
    "matchTime": "2026-06-23T03:00:00Z",
    "venue": "Levi's Stadium, San Francisco Bay Area",
    "group": "J",
    "stage": "group",
    "status": "pending"
  },
  {
    "id": "M059",
    "homeTeamId": "ALG",
    "awayTeamId": "AUT",
    "matchTime": "2026-06-28T02:00:00Z",
    "venue": "Arrowhead Stadium, Kansas City",
    "group": "J",
    "stage": "group",
    "status": "pending"
  },
  {
    "id": "M060",
    "homeTeamId": "JOR",
    "awayTeamId": "ARG",
    "matchTime": "2026-06-28T02:00:00Z",
    "venue": "AT&T Stadium, Dallas",
    "group": "J",
    "stage": "group",
    "status": "pending"
  },
  {
    "id": "M061",
    "homeTeamId": "POR",
    "awayTeamId": "COD",
    "matchTime": "2026-06-17T17:00:00Z",
    "venue": "NRG Stadium, Houston",
    "group": "K",
    "stage": "group",
    "status": "pending"
  },
  {
    "id": "M062",
    "homeTeamId": "UZB",
    "awayTeamId": "COL",
    "matchTime": "2026-06-18T02:00:00Z",
    "venue": "Estadio Azteca, Mexico City",
    "group": "K",
    "stage": "group",
    "status": "pending"
  },
  {
    "id": "M063",
    "homeTeamId": "POR",
    "awayTeamId": "UZB",
    "matchTime": "2026-06-23T17:00:00Z",
    "venue": "NRG Stadium, Houston",
    "group": "K",
    "stage": "group",
    "status": "pending"
  },
  {
    "id": "M064",
    "homeTeamId": "COL",
    "awayTeamId": "COD",
    "matchTime": "2026-06-24T02:00:00Z",
    "venue": "Estadio Akron, Guadalajara",
    "group": "K",
    "stage": "group",
    "status": "pending"
  },
  {
    "id": "M065",
    "homeTeamId": "COL",
    "awayTeamId": "POR",
    "matchTime": "2026-06-27T23:30:00Z",
    "venue": "Hard Rock Stadium, Miami",
    "group": "K",
    "stage": "group",
    "status": "pending"
  },
  {
    "id": "M066",
    "homeTeamId": "COD",
    "awayTeamId": "UZB",
    "matchTime": "2026-06-27T23:30:00Z",
    "venue": "Mercedes-Benz Stadium, Atlanta",
    "group": "K",
    "stage": "group",
    "status": "pending"
  },
  {
    "id": "M067",
    "homeTeamId": "ENG",
    "awayTeamId": "CRO",
    "matchTime": "2026-06-17T20:00:00Z",
    "venue": "AT&T Stadium, Dallas",
    "group": "L",
    "stage": "group",
    "status": "pending"
  },
  {
    "id": "M068",
    "homeTeamId": "GHA",
    "awayTeamId": "PAN",
    "matchTime": "2026-06-17T23:00:00Z",
    "venue": "BMO Field, Toronto",
    "group": "L",
    "stage": "group",
    "status": "pending"
  },
  {
    "id": "M069",
    "homeTeamId": "ENG",
    "awayTeamId": "GHA",
    "matchTime": "2026-06-23T20:00:00Z",
    "venue": "Gillette Stadium, Boston",
    "group": "L",
    "stage": "group",
    "status": "pending"
  },
  {
    "id": "M070",
    "homeTeamId": "PAN",
    "awayTeamId": "CRO",
    "matchTime": "2026-06-23T23:00:00Z",
    "venue": "BMO Field, Toronto",
    "group": "L",
    "stage": "group",
    "status": "pending"
  },
  {
    "id": "M071",
    "homeTeamId": "PAN",
    "awayTeamId": "ENG",
    "matchTime": "2026-06-27T21:00:00Z",
    "venue": "MetLife Stadium, New York/New Jersey",
    "group": "L",
    "stage": "group",
    "status": "pending"
  },
  {
    "id": "M072",
    "homeTeamId": "CRO",
    "awayTeamId": "GHA",
    "matchTime": "2026-06-27T21:00:00Z",
    "venue": "Lincoln Financial Field, Philadelphia",
    "group": "L",
    "stage": "group",
    "status": "pending"
  },
  {
    "id": "M073",
    "homeTeamId": "R32-H1",
    "awayTeamId": "R32-A1",
    "stage": "r32",
    "matchTime": "2026-06-28T17:00:00Z",
    "venue": "Estadio Azteca, Mexico City",
    "status": "pending"
  },
  {
    "id": "M074",
    "homeTeamId": "R32-H2",
    "awayTeamId": "R32-A2",
    "stage": "r32",
    "matchTime": "2026-06-28T20:00:00Z",
    "venue": "Estadio Akron, Guadalajara",
    "status": "pending"
  },
  {
    "id": "M075",
    "homeTeamId": "R32-H3",
    "awayTeamId": "R32-A3",
    "stage": "r32",
    "matchTime": "2026-06-28T23:00:00Z",
    "venue": "Estadio BBVA, Monterrey",
    "status": "pending"
  },
  {
    "id": "M076",
    "homeTeamId": "R32-H4",
    "awayTeamId": "R32-A4",
    "stage": "r32",
    "matchTime": "2026-06-29T17:00:00Z",
    "venue": "MetLife Stadium, New York/New Jersey",
    "status": "pending"
  },
  {
    "id": "M077",
    "homeTeamId": "R32-H5",
    "awayTeamId": "R32-A5",
    "stage": "r32",
    "matchTime": "2026-06-29T20:00:00Z",
    "venue": "SoFi Stadium, Los Angeles",
    "status": "pending"
  },
  {
    "id": "M078",
    "homeTeamId": "R32-H6",
    "awayTeamId": "R32-A6",
    "stage": "r32",
    "matchTime": "2026-06-29T23:00:00Z",
    "venue": "AT&T Stadium, Dallas",
    "status": "pending"
  },
  {
    "id": "M079",
    "homeTeamId": "R32-H7",
    "awayTeamId": "R32-A7",
    "stage": "r32",
    "matchTime": "2026-06-30T17:00:00Z",
    "venue": "NRG Stadium, Houston",
    "status": "pending"
  },
  {
    "id": "M080",
    "homeTeamId": "R32-H8",
    "awayTeamId": "R32-A8",
    "stage": "r32",
    "matchTime": "2026-06-30T20:00:00Z",
    "venue": "Hard Rock Stadium, Miami",
    "status": "pending"
  },
  {
    "id": "M081",
    "homeTeamId": "R32-H9",
    "awayTeamId": "R32-A9",
    "stage": "r32",
    "matchTime": "2026-06-30T23:00:00Z",
    "venue": "Lumen Field, Seattle",
    "status": "pending"
  },
  {
    "id": "M082",
    "homeTeamId": "R32-H10",
    "awayTeamId": "R32-A10",
    "stage": "r32",
    "matchTime": "2026-07-01T17:00:00Z",
    "venue": "Levi's Stadium, San Francisco Bay Area",
    "status": "pending"
  },
  {
    "id": "M083",
    "homeTeamId": "R32-H11",
    "awayTeamId": "R32-A11",
    "stage": "r32",
    "matchTime": "2026-07-01T20:00:00Z",
    "venue": "Mercedes-Benz Stadium, Atlanta",
    "status": "pending"
  },
  {
    "id": "M084",
    "homeTeamId": "R32-H12",
    "awayTeamId": "R32-A12",
    "stage": "r32",
    "matchTime": "2026-07-01T23:00:00Z",
    "venue": "Gillette Stadium, Boston",
    "status": "pending"
  },
  {
    "id": "M085",
    "homeTeamId": "R32-H13",
    "awayTeamId": "R32-A13",
    "stage": "r32",
    "matchTime": "2026-07-02T17:00:00Z",
    "venue": "Lincoln Financial Field, Philadelphia",
    "status": "pending"
  },
  {
    "id": "M086",
    "homeTeamId": "R32-H14",
    "awayTeamId": "R32-A14",
    "stage": "r32",
    "matchTime": "2026-07-02T20:00:00Z",
    "venue": "BC Place, Vancouver",
    "status": "pending"
  },
  {
    "id": "M087",
    "homeTeamId": "R32-H15",
    "awayTeamId": "R32-A15",
    "stage": "r32",
    "matchTime": "2026-07-02T23:00:00Z",
    "venue": "BMO Field, Toronto",
    "status": "pending"
  },
  {
    "id": "M088",
    "homeTeamId": "R32-H16",
    "awayTeamId": "R32-A16",
    "stage": "r32",
    "matchTime": "2026-07-03T17:00:00Z",
    "venue": "Arrowhead Stadium, Kansas City",
    "status": "pending"
  },
  {
    "id": "M089",
    "homeTeamId": "R16-H1",
    "awayTeamId": "R16-A1",
    "stage": "r16",
    "matchTime": "2026-07-04T19:00:00Z",
    "venue": "Estadio Azteca, Mexico City",
    "status": "pending"
  },
  {
    "id": "M090",
    "homeTeamId": "R16-H2",
    "awayTeamId": "R16-A2",
    "stage": "r16",
    "matchTime": "2026-07-04T23:00:00Z",
    "venue": "Estadio Akron, Guadalajara",
    "status": "pending"
  },
  {
    "id": "M091",
    "homeTeamId": "R16-H3",
    "awayTeamId": "R16-A3",
    "stage": "r16",
    "matchTime": "2026-07-05T19:00:00Z",
    "venue": "Estadio BBVA, Monterrey",
    "status": "pending"
  },
  {
    "id": "M092",
    "homeTeamId": "R16-H4",
    "awayTeamId": "R16-A4",
    "stage": "r16",
    "matchTime": "2026-07-05T23:00:00Z",
    "venue": "MetLife Stadium, New York/New Jersey",
    "status": "pending"
  },
  {
    "id": "M093",
    "homeTeamId": "R16-H5",
    "awayTeamId": "R16-A5",
    "stage": "r16",
    "matchTime": "2026-07-06T19:00:00Z",
    "venue": "SoFi Stadium, Los Angeles",
    "status": "pending"
  },
  {
    "id": "M094",
    "homeTeamId": "R16-H6",
    "awayTeamId": "R16-A6",
    "stage": "r16",
    "matchTime": "2026-07-06T23:00:00Z",
    "venue": "AT&T Stadium, Dallas",
    "status": "pending"
  },
  {
    "id": "M095",
    "homeTeamId": "R16-H7",
    "awayTeamId": "R16-A7",
    "stage": "r16",
    "matchTime": "2026-07-07T19:00:00Z",
    "venue": "NRG Stadium, Houston",
    "status": "pending"
  },
  {
    "id": "M096",
    "homeTeamId": "R16-H8",
    "awayTeamId": "R16-A8",
    "stage": "r16",
    "matchTime": "2026-07-07T23:00:00Z",
    "venue": "Hard Rock Stadium, Miami",
    "status": "pending"
  },
  {
    "id": "M097",
    "homeTeamId": "QF-H1",
    "awayTeamId": "QF-A1",
    "stage": "qf",
    "matchTime": "2026-07-09T20:00:00Z",
    "venue": "Gillette Stadium, Boston",
    "status": "pending"
  },
  {
    "id": "M098",
    "homeTeamId": "QF-H2",
    "awayTeamId": "QF-A2",
    "stage": "qf",
    "matchTime": "2026-07-10T19:00:00Z",
    "venue": "SoFi Stadium, Los Angeles",
    "status": "pending"
  },
  {
    "id": "M099",
    "homeTeamId": "QF-H3",
    "awayTeamId": "QF-A3",
    "stage": "qf",
    "matchTime": "2026-07-11T21:00:00Z",
    "venue": "Hard Rock Stadium, Miami",
    "status": "pending"
  },
  {
    "id": "M100",
    "homeTeamId": "QF-H4",
    "awayTeamId": "QF-A4",
    "stage": "qf",
    "matchTime": "2026-07-11T01:00:00Z",
    "venue": "Arrowhead Stadium, Kansas City",
    "status": "pending"
  },
  {
    "id": "M101",
    "homeTeamId": "SF-H1",
    "awayTeamId": "SF-A1",
    "stage": "sf",
    "matchTime": "2026-07-14T19:00:00Z",
    "venue": "AT&T Stadium, Dallas",
    "status": "pending"
  },
  {
    "id": "M102",
    "homeTeamId": "SF-H2",
    "awayTeamId": "SF-A2",
    "stage": "sf",
    "matchTime": "2026-07-15T19:00:00Z",
    "venue": "Mercedes-Benz Stadium, Atlanta",
    "status": "pending"
  },
  {
    "id": "M103",
    "homeTeamId": "THIRD-H1",
    "awayTeamId": "THIRD-A1",
    "stage": "third",
    "matchTime": "2026-07-18T21:00:00Z",
    "venue": "Hard Rock Stadium, Miami",
    "status": "pending"
  },
  {
    "id": "M104",
    "homeTeamId": "FINAL-H1",
    "awayTeamId": "FINAL-A1",
    "stage": "final",
    "matchTime": "2026-07-19T19:00:00Z",
    "venue": "MetLife Stadium, New York/New Jersey",
    "status": "pending"
  }
]